berxel_py_warpper/__init__.py
berxel_py_warpper/Python/__init__.py
berxel_py_warpper/Python/BerxelSdkDriver/BerxelHawkContext.py
berxel_py_warpper/Python/BerxelSdkDriver/BerxelHawkDefines.py
berxel_py_warpper/Python/BerxelSdkDriver/BerxelHawkDevice.py
berxel_py_warpper/Python/BerxelSdkDriver/BerxelHawkFrame.py
berxel_py_warpper/Python/BerxelSdkDriver/BerxelHawkNativeMethods.py
berxel_py_warpper/Python/BerxelSdkDriver/__init__.py
berxel_py_warpper/Python/BerxelSdkDriver/libs/linux/berxelLog.ini
berxel_py_warpper/Python/BerxelSdkDriver/libs/linux/libBerxelCommonDriver.so
berxel_py_warpper/Python/BerxelSdkDriver/libs/linux/libBerxelHawk.so
berxel_py_warpper/Python/BerxelSdkDriver/libs/linux/libBerxelInterface.so
berxel_py_warpper/Python/BerxelSdkDriver/libs/linux/libBerxelLogDriver.so
berxel_py_warpper/Python/BerxelSdkDriver/libs/linux/libBerxelNetDriver.so
berxel_py_warpper/Python/BerxelSdkDriver/libs/linux/libBerxelUvcDriver.so
berxel_py_warpper/Python/BerxelSdkDriver/libs/linux/params.bin
berxel_py_warpper/Python/BerxelSdkDriver/libs/linux/params100E.bin
berxel_py_warpper/Python/BerxelSdkDriver/libs/linux/params100Q.bin
berxel_py_warpper/Python/BerxelSdkDriver/libs/linux/params137_0.bin
berxel_py_warpper/Python/BerxelSdkDriver/libs/linux/params137_1.bin
berxel_py_warpper/Python/BerxelSdkDriver/libs/windows/BerxelCommonDriver.dll
berxel_py_warpper/Python/BerxelSdkDriver/libs/windows/BerxelHawk.dll
berxel_py_warpper/Python/BerxelSdkDriver/libs/windows/BerxelHawk.lib
berxel_py_warpper/Python/BerxelSdkDriver/libs/windows/BerxelInterface.dll
berxel_py_warpper/Python/BerxelSdkDriver/libs/windows/BerxelLogDriver.dll
berxel_py_warpper/Python/BerxelSdkDriver/libs/windows/BerxelNetDriver.dll
berxel_py_warpper/Python/BerxelSdkDriver/libs/windows/BerxelUvcDriver.dll
berxel_py_warpper/Python/BerxelSdkDriver/libs/windows/Packet.dll
berxel_py_warpper/Python/BerxelSdkDriver/libs/windows/SonixCamera.dll
berxel_py_warpper/Python/BerxelSdkDriver/libs/windows/berxelLog.ini
berxel_py_warpper-2.0.161.dist-info/licenses/LICENSE
berxel_py_warpper-2.0.161.dist-info/METADATA
berxel_py_warpper-2.0.161.dist-info/WHEEL
berxel_py_warpper-2.0.161.dist-info/top_level.txt
berxel_py_warpper-2.0.161.dist-info/RECORD
