Metadata-Version: 2.4
Name: berxel_py_warpper
Version: 2.0.161
Summary: Python wrapper for Berxel camera SDK - provides easy access to Berxel depth cameras
Author-email: Dong Zhaorui <joray.dong@hexfellow.com>
Maintainer-email: jecjune <zejun.chen@hexfellow.com>, Dong Zhaorui <joray.dong@hexfellow.com>
License-Expression: Apache-2.0
Project-URL: Homepage, https://www.hessian-matrix.com/
Project-URL: Documentation, https://www.hessian-matrix.com/%e4%b8%8b%e8%bd%bd%e4%b8%ad%e5%bf%83/
Project-URL: Repository, https://github.com/hexfellow/berxel_py_warpper
Project-URL: Bug Tracker, https://github.com/hexfellow/berxel_py_warpper/issues
Project-URL: Download, https://www.hessian-matrix.com/wp-content/uploads/2025/09/Python_2.0.161.zip
Keywords: berxel,camera,depth-camera,computer-vision,3d-vision,sdk,wrapper
Classifier: Development Status :: 4 - Beta
Classifier: Intended Audience :: Developers
Classifier: Intended Audience :: Science/Research
Classifier: Topic :: Multimedia :: Graphics :: Capture :: Digital Camera
Classifier: Topic :: Scientific/Engineering :: Image Processing
Classifier: Topic :: Software Development :: Libraries :: Python Modules
Classifier: Programming Language :: Python :: 3
Classifier: Programming Language :: Python :: 3.8
Classifier: Programming Language :: Python :: 3.9
Classifier: Programming Language :: Python :: 3.10
Classifier: Programming Language :: Python :: 3.11
Classifier: Programming Language :: Python :: 3.12
Classifier: Operating System :: OS Independent
Requires-Python: >=3.8
License-File: LICENSE
Requires-Dist: opencv-python>=4.2.0
Requires-Dist: numpy>=1.19.0
Dynamic: license-file
